st_card_component/__init__.py
st_card_component/frontend/build/asset-manifest.json
st_card_component/frontend/build/bootstrap.min.css
st_card_component/frontend/build/index.html
st_card_component/frontend/build/precache-manifest.1f866a8115f6dd83e0c8d1eb755ea353.js
st_card_component/frontend/build/service-worker.js
st_card_component/frontend/build/static/js/2.2e142390.chunk.js
st_card_component/frontend/build/static/js/2.2e142390.chunk.js.LICENSE.txt
st_card_component/frontend/build/static/js/2.2e142390.chunk.js.map
st_card_component/frontend/build/static/js/main.4195b895.chunk.js
st_card_component/frontend/build/static/js/main.4195b895.chunk.js.map
st_card_component/frontend/build/static/js/runtime-main.11ec9aca.js
st_card_component/frontend/build/static/js/runtime-main.11ec9aca.js.map
st_card_component-0.0.10.dist-info/LICENSE
st_card_component-0.0.10.dist-info/METADATA
st_card_component-0.0.10.dist-info/WHEEL
st_card_component-0.0.10.dist-info/top_level.txt
st_card_component-0.0.10.dist-info/RECORD
