Metadata-Version: 2.1
Name: st-card-component
Version: 0.0.10
Summary: Card component for Streamlit
Home-page: UNKNOWN
Author: James Briggs
Author-email: 
License: UNKNOWN
Platform: UNKNOWN
Requires-Python: >=3.6
Requires-Dist: streamlit (>=0.63)
